{
    "name": "fullRandom_large_569",
    "type": "TSP",
    "comment": "",
    "dimension": 323,
    "edge_weight_type": "EUC_2D",
    "node_coordinates": [
        [
            44977,
            78136
        ],
        [
            45237,
            28332
        ],
        [
            62995,
            12526
        ],
        [
            10509,
            19466
        ],
        [
            58429,
            44017
        ],
        [
            27913,
            51797
        ],
        [
            92056,
            8520
        ],
        [
            68669,
            7605
        ],
        [
            94840,
            38834
        ],
        [
            98247,
            60093
        ],
        [
            37424,
            97549
        ],
        [
            72806,
            77498
        ],
        [
            8766,
            42567
        ],
        [
            84468,
            96980
        ],
        [
            69536,
            27660
        ],
        [
            60320,
            60482
        ],
        [
            84189,
            53948
        ],
        [
            67029,
            14725
        ],
        [
            48259,
            49139
        ],
        [
            9066,
            43683
        ],
        [
            94970,
            92582
        ],
        [
            42252,
            98867
        ],
        [
            20936,
            24585
        ],
        [
            73728,
            82241
        ],
        [
            6044,
            68742
        ],
        [
            17721,
            41823
        ],
        [
            58432,
            40148
        ],
        [
            57061,
            43383
        ],
        [
            5767,
            42375
        ],
        [
            27099,
            35471
        ],
        [
            83942,
            78061
        ],
        [
            30783,
            62935
        ],
        [
            7049,
            29852
        ],
        [
            94238,
            39411
        ],
        [
            99140,
            70444
        ],
        [
            3156,
            30282
        ],
        [
            57797,
            4490
        ],
        [
            58083,
            63641
        ],
        [
            83871,
            99391
        ],
        [
            72266,
            5356
        ],
        [
            46407,
            27133
        ],
        [
            76406,
            78446
        ],
        [
            3074,
            23937
        ],
        [
            19641,
            82111
        ],
        [
            36657,
            65214
        ],
        [
            26943,
            66797
        ],
        [
            30859,
            9896
        ],
        [
            9449,
            9608
        ],
        [
            99932,
            55896
        ],
        [
            72678,
            181
        ],
        [
            87261,
            77014
        ],
        [
            80073,
            28301
        ],
        [
            12483,
            95744
        ],
        [
            97522,
            92946
        ],
        [
            37816,
            44780
        ],
        [
            32435,
            33983
        ],
        [
            88889,
            4590
        ],
        [
            12744,
            17346
        ],
        [
            53064,
            56699
        ],
        [
            20116,
            94462
        ],
        [
            59398,
            34939
        ],
        [
            54290,
            57281
        ],
        [
            28872,
            64713
        ],
        [
            97480,
            99054
        ],
        [
            72364,
            24519
        ],
        [
            49684,
            58360
        ],
        [
            81522,
            63023
        ],
        [
            14940,
            26046
        ],
        [
            92898,
            12354
        ],
        [
            26378,
            78936
        ],
        [
            9500,
            23818
        ],
        [
            54467,
            51519
        ],
        [
            92333,
            59517
        ],
        [
            12412,
            13733
        ],
        [
            46750,
            22241
        ],
        [
            61380,
            31781
        ],
        [
            28723,
            83443
        ],
        [
            93361,
            26762
        ],
        [
            98707,
            93644
        ],
        [
            76066,
            90541
        ],
        [
            87760,
            39563
        ],
        [
            47920,
            75498
        ],
        [
            65688,
            91301
        ],
        [
            97196,
            20076
        ],
        [
            79268,
            31243
        ],
        [
            99116,
            30088
        ],
        [
            46096,
            77281
        ],
        [
            49233,
            14673
        ],
        [
            69940,
            76572
        ],
        [
            22723,
            47442
        ],
        [
            26788,
            9771
        ],
        [
            92402,
            6884
        ],
        [
            12235,
            70415
        ],
        [
            19514,
            76179
        ],
        [
            68531,
            73111
        ],
        [
            55846,
            72559
        ],
        [
            30766,
            92760
        ],
        [
            48229,
            52559
        ],
        [
            55684,
            60988
        ],
        [
            70323,
            18777
        ],
        [
            27611,
            11895
        ],
        [
            34566,
            82774
        ],
        [
            57617,
            31321
        ],
        [
            54725,
            19006
        ],
        [
            57928,
            29813
        ],
        [
            16312,
            56700
        ],
        [
            50923,
            98980
        ],
        [
            19616,
            61532
        ],
        [
            68050,
            89388
        ],
        [
            19369,
            83445
        ],
        [
            83143,
            57902
        ],
        [
            33595,
            73777
        ],
        [
            33866,
            92391
        ],
        [
            80913,
            32517
        ],
        [
            27464,
            79186
        ],
        [
            26467,
            88619
        ],
        [
            11027,
            27152
        ],
        [
            96644,
            89378
        ],
        [
            90038,
            38249
        ],
        [
            3704,
            15853
        ],
        [
            67871,
            23096
        ],
        [
            1946,
            37144
        ],
        [
            3645,
            96563
        ],
        [
            14042,
            83138
        ],
        [
            81722,
            54957
        ],
        [
            24240,
            65877
        ],
        [
            75323,
            36480
        ],
        [
            54807,
            46895
        ],
        [
            25917,
            29554
        ],
        [
            31031,
            69692
        ],
        [
            54962,
            38777
        ],
        [
            37857,
            91296
        ],
        [
            20434,
            90246
        ],
        [
            29509,
            41778
        ],
        [
            70163,
            94047
        ],
        [
            63767,
            48399
        ],
        [
            60211,
            68892
        ],
        [
            69534,
            57437
        ],
        [
            65865,
            58121
        ],
        [
            30463,
            27385
        ],
        [
            91379,
            28514
        ],
        [
            71123,
            17340
        ],
        [
            96427,
            28761
        ],
        [
            57681,
            9879
        ],
        [
            99008,
            48377
        ],
        [
            28665,
            44825
        ],
        [
            4392,
            59364
        ],
        [
            2084,
            70332
        ],
        [
            59511,
            61203
        ],
        [
            7569,
            97270
        ],
        [
            37999,
            59107
        ],
        [
            91005,
            44977
        ],
        [
            69665,
            23141
        ],
        [
            47338,
            81603
        ],
        [
            72868,
            50981
        ],
        [
            62863,
            20458
        ],
        [
            27770,
            54795
        ],
        [
            43531,
            66868
        ],
        [
            67209,
            98445
        ],
        [
            44727,
            71988
        ],
        [
            64094,
            38962
        ],
        [
            23106,
            56745
        ],
        [
            2795,
            24682
        ],
        [
            73339,
            2803
        ],
        [
            34268,
            33419
        ],
        [
            14734,
            72996
        ],
        [
            63377,
            53874
        ],
        [
            76588,
            5960
        ],
        [
            31536,
            96948
        ],
        [
            16595,
            11533
        ],
        [
            40697,
            40302
        ],
        [
            87268,
            57668
        ],
        [
            38618,
            69814
        ],
        [
            73302,
            19682
        ],
        [
            95250,
            52183
        ],
        [
            87871,
            21549
        ],
        [
            56024,
            48951
        ],
        [
            45423,
            9504
        ],
        [
            805,
            20463
        ],
        [
            90400,
            87718
        ],
        [
            65474,
            50796
        ],
        [
            94513,
            35170
        ],
        [
            60501,
            81550
        ],
        [
            79607,
            18574
        ],
        [
            52101,
            42741
        ],
        [
            2067,
            68147
        ],
        [
            33941,
            83329
        ],
        [
            91246,
            86746
        ],
        [
            2164,
            24888
        ],
        [
            82996,
            42307
        ],
        [
            27876,
            41517
        ],
        [
            36163,
            49100
        ],
        [
            59274,
            28415
        ],
        [
            2361,
            63328
        ],
        [
            95688,
            74400
        ],
        [
            13784,
            87486
        ],
        [
            20210,
            90198
        ],
        [
            10157,
            1942
        ],
        [
            96139,
            13817
        ],
        [
            53718,
            67054
        ],
        [
            10503,
            36219
        ],
        [
            65823,
            88540
        ],
        [
            76469,
            50206
        ],
        [
            69497,
            38056
        ],
        [
            50354,
            11608
        ],
        [
            67797,
            4881
        ],
        [
            67595,
            92296
        ],
        [
            6094,
            15582
        ],
        [
            3635,
            82169
        ],
        [
            93732,
            96669
        ],
        [
            74355,
            5369
        ],
        [
            69825,
            71435
        ],
        [
            20746,
            91740
        ],
        [
            63324,
            86756
        ],
        [
            5342,
            78896
        ],
        [
            38254,
            29794
        ],
        [
            81328,
            72041
        ],
        [
            6520,
            18682
        ],
        [
            76868,
            36547
        ],
        [
            91852,
            72265
        ],
        [
            37689,
            42512
        ],
        [
            49307,
            6974
        ],
        [
            99234,
            57971
        ],
        [
            33058,
            73330
        ],
        [
            50098,
            34180
        ],
        [
            56201,
            47705
        ],
        [
            69715,
            27680
        ],
        [
            76305,
            48557
        ],
        [
            3684,
            31027
        ],
        [
            99463,
            51842
        ],
        [
            30661,
            64894
        ],
        [
            51495,
            1886
        ],
        [
            46267,
            73383
        ],
        [
            1621,
            85728
        ],
        [
            70831,
            85625
        ],
        [
            96493,
            49257
        ],
        [
            58674,
            87972
        ],
        [
            3809,
            37983
        ],
        [
            66106,
            46568
        ],
        [
            66687,
            83577
        ],
        [
            74430,
            29310
        ],
        [
            21965,
            58764
        ],
        [
            65700,
            43502
        ],
        [
            44133,
            23079
        ],
        [
            36951,
            28809
        ],
        [
            73056,
            24357
        ],
        [
            1521,
            7112
        ],
        [
            26989,
            71728
        ],
        [
            69189,
            9662
        ],
        [
            43414,
            70542
        ],
        [
            3912,
            17397
        ],
        [
            26846,
            51883
        ],
        [
            1444,
            86955
        ],
        [
            79499,
            90617
        ],
        [
            78965,
            40837
        ],
        [
            93100,
            64786
        ],
        [
            65068,
            60285
        ],
        [
            31898,
            29563
        ],
        [
            60921,
            37161
        ],
        [
            75161,
            52463
        ],
        [
            29288,
            22333
        ],
        [
            16976,
            88223
        ],
        [
            6754,
            7220
        ],
        [
            85974,
            24902
        ],
        [
            59321,
            63479
        ],
        [
            49650,
            59561
        ],
        [
            83967,
            68394
        ],
        [
            95890,
            36092
        ],
        [
            81150,
            25633
        ],
        [
            79895,
            99858
        ],
        [
            43005,
            28750
        ],
        [
            10425,
            90702
        ],
        [
            35112,
            27593
        ],
        [
            87444,
            8879
        ],
        [
            8965,
            702
        ],
        [
            18432,
            72724
        ],
        [
            74380,
            32240
        ],
        [
            79420,
            14530
        ],
        [
            3019,
            97192
        ],
        [
            51037,
            97277
        ],
        [
            41339,
            12477
        ],
        [
            79747,
            72804
        ],
        [
            44149,
            20277
        ],
        [
            88295,
            27926
        ],
        [
            89006,
            5924
        ],
        [
            57438,
            10888
        ],
        [
            87699,
            48919
        ],
        [
            54899,
            2912
        ],
        [
            44554,
            34118
        ],
        [
            19691,
            86111
        ],
        [
            91936,
            30405
        ],
        [
            95593,
            27448
        ],
        [
            637,
            8491
        ],
        [
            31991,
            94912
        ],
        [
            78762,
            85575
        ],
        [
            51962,
            88924
        ],
        [
            61967,
            81134
        ],
        [
            23276,
            36940
        ],
        [
            1081,
            74785
        ],
        [
            64410,
            67376
        ],
        [
            70059,
            31658
        ],
        [
            73599,
            61269
        ],
        [
            7487,
            32787
        ],
        [
            88464,
            77874
        ],
        [
            1532,
            40649
        ],
        [
            49420,
            67771
        ],
        [
            50857,
            51370
        ],
        [
            77776,
            82349
        ],
        [
            69571,
            65611
        ],
        [
            44206,
            8506
        ],
        [
            86749,
            75094
        ],
        [
            34082,
            24414
        ],
        [
            60259,
            44002
        ],
        [
            91066,
            59104
        ],
        [
            10271,
            37279
        ],
        [
            70310,
            12513
        ],
        [
            29452,
            67995
        ],
        [
            99838,
            30920
        ],
        [
            27558,
            82816
        ],
        [
            61750,
            19645
        ],
        [
            87103,
            31215
        ],
        [
            54783,
            41918
        ],
        [
            79328,
            72139
        ]
    ]
}