{
    "name": "fullRandom_large_856",
    "type": "TSP",
    "comment": "",
    "dimension": 479,
    "edge_weight_type": "EUC_2D",
    "node_coordinates": [
        [
            54422,
            39569
        ],
        [
            40908,
            76556
        ],
        [
            91991,
            44399
        ],
        [
            87875,
            95776
        ],
        [
            70106,
            46193
        ],
        [
            68204,
            53852
        ],
        [
            63767,
            33946
        ],
        [
            14509,
            62775
        ],
        [
            19141,
            29168
        ],
        [
            17267,
            70901
        ],
        [
            62431,
            34269
        ],
        [
            92917,
            44154
        ],
        [
            88616,
            37758
        ],
        [
            71738,
            89181
        ],
        [
            51944,
            48307
        ],
        [
            30019,
            75009
        ],
        [
            57265,
            70634
        ],
        [
            35154,
            53706
        ],
        [
            80274,
            70351
        ],
        [
            89133,
            28184
        ],
        [
            80611,
            20965
        ],
        [
            49642,
            48895
        ],
        [
            77397,
            30025
        ],
        [
            33449,
            23815
        ],
        [
            54092,
            1294
        ],
        [
            3739,
            5340
        ],
        [
            31391,
            78728
        ],
        [
            28445,
            87061
        ],
        [
            10636,
            96661
        ],
        [
            60271,
            28305
        ],
        [
            60020,
            93727
        ],
        [
            70491,
            41548
        ],
        [
            1586,
            51294
        ],
        [
            62410,
            36510
        ],
        [
            86002,
            19018
        ],
        [
            85656,
            83509
        ],
        [
            50333,
            70484
        ],
        [
            69284,
            51509
        ],
        [
            56620,
            26612
        ],
        [
            86705,
            4314
        ],
        [
            46951,
            99844
        ],
        [
            64746,
            57340
        ],
        [
            21652,
            59864
        ],
        [
            7215,
            88600
        ],
        [
            18489,
            44112
        ],
        [
            59757,
            64972
        ],
        [
            75005,
            77799
        ],
        [
            23665,
            81970
        ],
        [
            14128,
            73066
        ],
        [
            19632,
            33868
        ],
        [
            75444,
            39873
        ],
        [
            39100,
            80011
        ],
        [
            65351,
            29982
        ],
        [
            46271,
            74027
        ],
        [
            91298,
            95570
        ],
        [
            99763,
            20587
        ],
        [
            84425,
            2948
        ],
        [
            61903,
            83651
        ],
        [
            9810,
            71184
        ],
        [
            70822,
            65286
        ],
        [
            10457,
            93903
        ],
        [
            18779,
            79143
        ],
        [
            66492,
            48002
        ],
        [
            98101,
            17835
        ],
        [
            49474,
            88880
        ],
        [
            47538,
            46590
        ],
        [
            94505,
            63180
        ],
        [
            2207,
            65122
        ],
        [
            23694,
            68074
        ],
        [
            35928,
            74714
        ],
        [
            66450,
            99600
        ],
        [
            73933,
            70792
        ],
        [
            83742,
            24823
        ],
        [
            99627,
            65967
        ],
        [
            11823,
            48211
        ],
        [
            24751,
            85353
        ],
        [
            40444,
            14100
        ],
        [
            61889,
            15102
        ],
        [
            40263,
            87596
        ],
        [
            20999,
            89075
        ],
        [
            4831,
            97064
        ],
        [
            99648,
            99580
        ],
        [
            71719,
            10173
        ],
        [
            60766,
            40645
        ],
        [
            38166,
            92856
        ],
        [
            60143,
            87261
        ],
        [
            98755,
            34677
        ],
        [
            44587,
            11503
        ],
        [
            97554,
            56190
        ],
        [
            81278,
            2600
        ],
        [
            34377,
            42979
        ],
        [
            49684,
            70541
        ],
        [
            80370,
            98484
        ],
        [
            95278,
            8074
        ],
        [
            93925,
            35055
        ],
        [
            81759,
            94530
        ],
        [
            11149,
            16022
        ],
        [
            59231,
            16273
        ],
        [
            45435,
            75858
        ],
        [
            2586,
            61509
        ],
        [
            25991,
            61396
        ],
        [
            97505,
            24988
        ],
        [
            24296,
            5633
        ],
        [
            42661,
            28514
        ],
        [
            11881,
            70583
        ],
        [
            73892,
            29173
        ],
        [
            41108,
            12375
        ],
        [
            3843,
            74833
        ],
        [
            14610,
            82133
        ],
        [
            91932,
            54801
        ],
        [
            35417,
            85990
        ],
        [
            70475,
            46035
        ],
        [
            30434,
            97559
        ],
        [
            74287,
            29994
        ],
        [
            48015,
            46445
        ],
        [
            4298,
            19877
        ],
        [
            31262,
            3360
        ],
        [
            71528,
            21691
        ],
        [
            4269,
            36409
        ],
        [
            41332,
            13868
        ],
        [
            68772,
            94263
        ],
        [
            28593,
            87802
        ],
        [
            7335,
            29506
        ],
        [
            47473,
            3208
        ],
        [
            11528,
            32140
        ],
        [
            83724,
            9018
        ],
        [
            78630,
            11386
        ],
        [
            18676,
            91882
        ],
        [
            19859,
            5549
        ],
        [
            57845,
            6927
        ],
        [
            11166,
            2550
        ],
        [
            13774,
            53773
        ],
        [
            29960,
            67487
        ],
        [
            94890,
            1853
        ],
        [
            91964,
            43461
        ],
        [
            77727,
            71363
        ],
        [
            66644,
            27826
        ],
        [
            80009,
            57204
        ],
        [
            31183,
            47199
        ],
        [
            33235,
            43196
        ],
        [
            2648,
            91222
        ],
        [
            72815,
            55193
        ],
        [
            53661,
            36640
        ],
        [
            28651,
            17196
        ],
        [
            23858,
            10954
        ],
        [
            77277,
            33619
        ],
        [
            9258,
            87379
        ],
        [
            17459,
            24427
        ],
        [
            11441,
            48196
        ],
        [
            77323,
            20974
        ],
        [
            6200,
            1707
        ],
        [
            25836,
            3363
        ],
        [
            1197,
            34932
        ],
        [
            6667,
            16888
        ],
        [
            3833,
            30093
        ],
        [
            50616,
            2613
        ],
        [
            67019,
            26874
        ],
        [
            92415,
            2736
        ],
        [
            91321,
            58134
        ],
        [
            31587,
            32332
        ],
        [
            69092,
            59241
        ],
        [
            11201,
            93051
        ],
        [
            12053,
            39965
        ],
        [
            35067,
            92048
        ],
        [
            62509,
            85076
        ],
        [
            37255,
            42216
        ],
        [
            87307,
            16680
        ],
        [
            29651,
            25193
        ],
        [
            95122,
            34724
        ],
        [
            13574,
            3171
        ],
        [
            43567,
            89206
        ],
        [
            26273,
            34615
        ],
        [
            716,
            54899
        ],
        [
            46832,
            19575
        ],
        [
            27740,
            84670
        ],
        [
            24499,
            15224
        ],
        [
            65912,
            12025
        ],
        [
            87013,
            71184
        ],
        [
            69602,
            3322
        ],
        [
            59354,
            18725
        ],
        [
            90290,
            39372
        ],
        [
            58792,
            49288
        ],
        [
            93422,
            70091
        ],
        [
            72255,
            90974
        ],
        [
            64021,
            80062
        ],
        [
            9514,
            54226
        ],
        [
            33319,
            85038
        ],
        [
            42740,
            47812
        ],
        [
            13336,
            18940
        ],
        [
            3284,
            16671
        ],
        [
            59857,
            25861
        ],
        [
            42175,
            8780
        ],
        [
            50384,
            82600
        ],
        [
            17012,
            71936
        ],
        [
            74223,
            37405
        ],
        [
            20782,
            86458
        ],
        [
            49580,
            85034
        ],
        [
            28098,
            65057
        ],
        [
            3119,
            78012
        ],
        [
            84996,
            57305
        ],
        [
            48285,
            56179
        ],
        [
            61324,
            77829
        ],
        [
            22218,
            17139
        ],
        [
            67642,
            38601
        ],
        [
            88839,
            19522
        ],
        [
            91554,
            64067
        ],
        [
            31510,
            88543
        ],
        [
            70573,
            59069
        ],
        [
            8663,
            67933
        ],
        [
            62526,
            66057
        ],
        [
            98323,
            20619
        ],
        [
            66978,
            42258
        ],
        [
            87174,
            57115
        ],
        [
            52104,
            1661
        ],
        [
            95918,
            45865
        ],
        [
            86176,
            75223
        ],
        [
            5823,
            70012
        ],
        [
            51313,
            36836
        ],
        [
            17564,
            16729
        ],
        [
            49316,
            89947
        ],
        [
            24656,
            85374
        ],
        [
            1757,
            79029
        ],
        [
            49126,
            48874
        ],
        [
            14803,
            83313
        ],
        [
            8914,
            65719
        ],
        [
            52146,
            38113
        ],
        [
            98037,
            8315
        ],
        [
            1867,
            40221
        ],
        [
            45159,
            92983
        ],
        [
            78572,
            71263
        ],
        [
            39465,
            16418
        ],
        [
            44586,
            45010
        ],
        [
            80071,
            12120
        ],
        [
            25771,
            63319
        ],
        [
            20204,
            8059
        ],
        [
            92235,
            14875
        ],
        [
            69541,
            73667
        ],
        [
            55981,
            80211
        ],
        [
            69891,
            60291
        ],
        [
            38440,
            46149
        ],
        [
            94567,
            46014
        ],
        [
            28866,
            51448
        ],
        [
            63123,
            66816
        ],
        [
            28939,
            3728
        ],
        [
            49690,
            85863
        ],
        [
            66748,
            99740
        ],
        [
            56628,
            56416
        ],
        [
            80569,
            79611
        ],
        [
            60637,
            98416
        ],
        [
            84896,
            82913
        ],
        [
            9572,
            75238
        ],
        [
            40538,
            84091
        ],
        [
            90263,
            46355
        ],
        [
            69832,
            8508
        ],
        [
            60056,
            98282
        ],
        [
            5255,
            77937
        ],
        [
            83404,
            98979
        ],
        [
            90909,
            71425
        ],
        [
            49640,
            12832
        ],
        [
            89490,
            61939
        ],
        [
            48846,
            87574
        ],
        [
            28947,
            68846
        ],
        [
            83431,
            29718
        ],
        [
            78737,
            36629
        ],
        [
            4514,
            4130
        ],
        [
            81367,
            35772
        ],
        [
            26786,
            90706
        ],
        [
            82604,
            16464
        ],
        [
            83215,
            69103
        ],
        [
            88391,
            95465
        ],
        [
            8507,
            67043
        ],
        [
            18418,
            97960
        ],
        [
            60283,
            51775
        ],
        [
            70615,
            75466
        ],
        [
            7002,
            31797
        ],
        [
            63711,
            10474
        ],
        [
            49173,
            2096
        ],
        [
            18469,
            41377
        ],
        [
            68057,
            52091
        ],
        [
            49377,
            7580
        ],
        [
            55997,
            66143
        ],
        [
            68880,
            76474
        ],
        [
            38078,
            48369
        ],
        [
            72882,
            11494
        ],
        [
            86104,
            3007
        ],
        [
            4450,
            41938
        ],
        [
            26986,
            78969
        ],
        [
            23266,
            52707
        ],
        [
            98180,
            25929
        ],
        [
            43792,
            33246
        ],
        [
            54989,
            38732
        ],
        [
            5821,
            61751
        ],
        [
            51171,
            50353
        ],
        [
            31280,
            65717
        ],
        [
            64347,
            80165
        ],
        [
            78045,
            67308
        ],
        [
            15410,
            62954
        ],
        [
            90174,
            73580
        ],
        [
            81874,
            33383
        ],
        [
            21544,
            27359
        ],
        [
            39880,
            66086
        ],
        [
            99709,
            37758
        ],
        [
            91639,
            77968
        ],
        [
            48326,
            91740
        ],
        [
            81891,
            52859
        ],
        [
            18604,
            16789
        ],
        [
            17089,
            66963
        ],
        [
            10215,
            20176
        ],
        [
            86500,
            21238
        ],
        [
            2109,
            78376
        ],
        [
            30939,
            69086
        ],
        [
            99369,
            16663
        ],
        [
            26186,
            73940
        ],
        [
            20292,
            96270
        ],
        [
            11976,
            75484
        ],
        [
            4187,
            75980
        ],
        [
            71959,
            25699
        ],
        [
            69328,
            86
        ],
        [
            63948,
            31183
        ],
        [
            9076,
            43830
        ],
        [
            98520,
            4205
        ],
        [
            31603,
            606
        ],
        [
            77038,
            71798
        ],
        [
            53440,
            37925
        ],
        [
            73894,
            74193
        ],
        [
            93053,
            7063
        ],
        [
            37652,
            33811
        ],
        [
            11613,
            22793
        ],
        [
            61982,
            81199
        ],
        [
            87729,
            39399
        ],
        [
            88246,
            62097
        ],
        [
            90375,
            14904
        ],
        [
            64402,
            5486
        ],
        [
            81926,
            38546
        ],
        [
            18845,
            93560
        ],
        [
            10849,
            84032
        ],
        [
            43299,
            75790
        ],
        [
            29667,
            45160
        ],
        [
            68389,
            18619
        ],
        [
            8570,
            6760
        ],
        [
            58822,
            64068
        ],
        [
            49660,
            18178
        ],
        [
            45265,
            45757
        ],
        [
            23249,
            84330
        ],
        [
            28979,
            70763
        ],
        [
            2819,
            79580
        ],
        [
            77710,
            69670
        ],
        [
            65925,
            74386
        ],
        [
            79216,
            32648
        ],
        [
            85262,
            96643
        ],
        [
            93257,
            2623
        ],
        [
            64175,
            42406
        ],
        [
            15938,
            863
        ],
        [
            10672,
            44100
        ],
        [
            9892,
            69860
        ],
        [
            52949,
            65502
        ],
        [
            85243,
            65953
        ],
        [
            85487,
            19058
        ],
        [
            12774,
            64383
        ],
        [
            78948,
            99494
        ],
        [
            87929,
            40762
        ],
        [
            69654,
            28697
        ],
        [
            18628,
            70886
        ],
        [
            87843,
            22643
        ],
        [
            6172,
            72852
        ],
        [
            48645,
            19153
        ],
        [
            25973,
            61152
        ],
        [
            87463,
            495
        ],
        [
            11403,
            77597
        ],
        [
            98279,
            83552
        ],
        [
            71830,
            21974
        ],
        [
            22391,
            85248
        ],
        [
            32182,
            67479
        ],
        [
            98970,
            91884
        ],
        [
            82719,
            94958
        ],
        [
            37795,
            30982
        ],
        [
            21777,
            48449
        ],
        [
            80461,
            39166
        ],
        [
            24139,
            67994
        ],
        [
            8879,
            20618
        ],
        [
            30035,
            75612
        ],
        [
            92964,
            30136
        ],
        [
            69767,
            53865
        ],
        [
            29513,
            66534
        ],
        [
            53254,
            52935
        ],
        [
            39114,
            14898
        ],
        [
            14882,
            40727
        ],
        [
            47778,
            92195
        ],
        [
            14577,
            35556
        ],
        [
            37534,
            30542
        ],
        [
            41053,
            68551
        ],
        [
            59144,
            63736
        ],
        [
            9855,
            89130
        ],
        [
            28959,
            14242
        ],
        [
            84998,
            50096
        ],
        [
            77042,
            36609
        ],
        [
            80679,
            28262
        ],
        [
            69275,
            97054
        ],
        [
            75973,
            12252
        ],
        [
            82347,
            39319
        ],
        [
            73259,
            32605
        ],
        [
            8254,
            73369
        ],
        [
            27428,
            88189
        ],
        [
            18440,
            6173
        ],
        [
            98782,
            45327
        ],
        [
            83549,
            88434
        ],
        [
            38094,
            84781
        ],
        [
            29797,
            91764
        ],
        [
            90428,
            20268
        ],
        [
            55695,
            22584
        ],
        [
            3748,
            12277
        ],
        [
            22895,
            4558
        ],
        [
            98061,
            4936
        ],
        [
            93567,
            84402
        ],
        [
            55666,
            11912
        ],
        [
            25364,
            32250
        ],
        [
            7587,
            77863
        ],
        [
            96794,
            49708
        ],
        [
            12424,
            15557
        ],
        [
            41465,
            15796
        ],
        [
            85649,
            91198
        ],
        [
            5350,
            54142
        ],
        [
            79936,
            84129
        ],
        [
            11993,
            49108
        ],
        [
            10290,
            74687
        ],
        [
            89785,
            55231
        ],
        [
            12184,
            22913
        ],
        [
            38832,
            27684
        ],
        [
            28280,
            75226
        ],
        [
            67600,
            23963
        ],
        [
            93947,
            16844
        ],
        [
            55465,
            93751
        ],
        [
            8484,
            44316
        ],
        [
            80464,
            24557
        ],
        [
            82647,
            78073
        ],
        [
            95087,
            22331
        ],
        [
            35790,
            39792
        ],
        [
            20989,
            71760
        ],
        [
            55865,
            28476
        ],
        [
            99052,
            24127
        ],
        [
            52748,
            71633
        ],
        [
            28648,
            83446
        ],
        [
            11166,
            58611
        ],
        [
            6725,
            74544
        ],
        [
            58729,
            55450
        ],
        [
            78034,
            35151
        ],
        [
            19447,
            71988
        ],
        [
            82957,
            89504
        ],
        [
            65225,
            68571
        ],
        [
            33152,
            11754
        ],
        [
            52978,
            18385
        ],
        [
            59663,
            21793
        ],
        [
            89124,
            73561
        ],
        [
            68682,
            54891
        ],
        [
            86507,
            65234
        ],
        [
            84194,
            20538
        ],
        [
            79434,
            49186
        ],
        [
            48317,
            39987
        ],
        [
            56413,
            40399
        ],
        [
            76169,
            80939
        ],
        [
            21640,
            23340
        ],
        [
            4665,
            53814
        ],
        [
            68991,
            83437
        ],
        [
            949,
            50461
        ],
        [
            2183,
            52119
        ],
        [
            60972,
            10206
        ],
        [
            28062,
            61845
        ],
        [
            80368,
            57553
        ],
        [
            53441,
            32860
        ],
        [
            48092,
            72820
        ],
        [
            3742,
            79589
        ],
        [
            90160,
            70803
        ],
        [
            17683,
            89112
        ],
        [
            43659,
            25369
        ],
        [
            37585,
            9733
        ],
        [
            21434,
            6751
        ],
        [
            49877,
            31615
        ],
        [
            85695,
            30768
        ],
        [
            74461,
            94263
        ]
    ]
}